{
    "wordsArr" : [
        ["C", "S", "T", "A", "R", "I", "Q", "R", "U", "O", "C", "A", "V", "L", "T", "R", "I", "A", "N", "G", "L", "E", "E", "L"],
        ["H", "C", "A", "T", "D", "O", "G", "A", "R", "M", "S", "H", "E", "E", "P", "E", "L"]
    ],

    "object0" : [
        [4, 9, 12, 17, 23],
        [5, 0, 5, 8, 10, 15]
    ],

    "object1" : [
        [6, 1, 6, 8, 11, 15, 22],
        [3, 4, 5, 6]
    ],

    "object2" : [
        [4, 1, 2, 3, 4],
        [5, 1, 7, 9, 13, 16]
    ],

    "object3" : [
        [8, 14, 15, 16, 17, 18, 19, 20, 21],
        [3, 1, 2, 3]
    ],

    "object4" : [
        [6, 0, 5, 7, 10, 13, 21],
        [5, 10, 11, 12, 13, 14]
    ],

    "belongTo" : [
        [[5], [2, 3], [3], [3], [3], [5], [2], [5], [2], [1], [5], [2], [1], [5], [4], [2, 4], [4], [1, 4], [4], [4], [4], [4, 5], [2], [1]],
        [[1], [3, 4, 5], [4], [4], [2], [1, 2], [2], [3], [1], [3], [1, 5], [5], [5], [3, 5], [5], [1], [3]]
    ],

    "ObjectPositions" : [
        [[979, 374], [450, 120], [450, 410], [1305, 625], [1325, 130]],
        [[488, 150], [500, 500], [1300, 150], [1400, 400], [1300, 650]]
    ],

    "blockPositions" : [
        [[1128, 159], [648, 239], [728, 239], [808, 239], [888, 239], [1128, 239], [648, 319], [1128, 319], [648, 399], [808, 399], [1128, 399], [648, 479], [808, 479], [1128, 479], [568, 559], [648, 559], [728, 559], [808, 559], [888, 559], [968, 559], [1048, 559], [1128, 559], [648, 639], [808, 639]],
        [[728, 239], [968, 239], [1048, 239], [1128, 239], [648, 319], [728, 319], [808, 319], [968, 319], [728, 399], [968, 399], [728, 479], [808, 479], [888, 479], [968, 479], [1048, 479], [728, 559], [968, 559]]
    ],

    "arrowSmallPositionsAndAngles" : [
        [[600, 170, 30], [860, 330, 330], [1176, 104, 0], [1231, 554, 0]]
    ],

    "arrowPositionsAndAngles" : [
        [[520, 250, 340]]
    ]
}